pyoptional/__init__.py
pyoptional/optional.py
pyoptional/try_functional.py
optional_python-0.0.2.dist-info/LICENSE
optional_python-0.0.2.dist-info/METADATA
optional_python-0.0.2.dist-info/WHEEL
optional_python-0.0.2.dist-info/RECORD
