Metadata-Version: 2.1
Name: optional-python
Version: 0.0.2
Summary: Optional object for python
Home-page: https://github.com/ponytailer/PyOptional
Author: ponytailer
Author-email: huangxiaohen2738@gmail.com
Requires-Python: >=3.8,<4.0
Classifier: Programming Language :: Python :: 3
Classifier: Programming Language :: Python :: 3.8
Classifier: Programming Language :: Python :: 3.9
Classifier: Programming Language :: Python :: 3.10
Classifier: Programming Language :: Python :: 3.11
